adapter/__init__.py
adapter/__main__.py
adapter/main.py
core/__init__.py
core/exception.py
core/judger.py
core/logger.py
core/protocol.py
core/summary.py
core/utils.py
judger_cli/__init__.py
judger_cli/__main__.py
judger_cli/cli.py
saiblo_local_judger-0.0.2.dist-info/LICENSE.txt
saiblo_local_judger-0.0.2.dist-info/METADATA
saiblo_local_judger-0.0.2.dist-info/WHEEL
saiblo_local_judger-0.0.2.dist-info/entry_points.txt
saiblo_local_judger-0.0.2.dist-info/top_level.txt
saiblo_local_judger-0.0.2.dist-info/RECORD
