Metadata-Version: 2.1
Name: saiblo-local-judger
Version: 0.0.2
Summary: Saiblo Local Judger
Home-page: https://github.com/saiblo/saiblo-local-judger
Author: xsun2001
Author-email: xcx14@outlook.com
License: UNKNOWN
Project-URL: Bug Tracker, https://github.com/saiblo/saiblo-local-judger/issues
Platform: UNKNOWN
Classifier: Programming Language :: Python :: 3
Classifier: License :: OSI Approved :: MIT License
Classifier: Operating System :: OS Independent
Requires-Python: >=3.7
License-File: LICENSE.txt
